LICENSE
MANIFEST.in
README.md
setup.cfg
setup.py
tap_toast/__init__.py
tap_toast/context.py
tap_toast/discover.py
tap_toast/streams.py
tap_toast/sync.py
tap_toast/toast.py
tap_toast.egg-info/PKG-INFO
tap_toast.egg-info/SOURCES.txt
tap_toast.egg-info/dependency_links.txt
tap_toast.egg-info/entry_points.txt
tap_toast.egg-info/requires.txt
tap_toast.egg-info/top_level.txt
tap_toast/schemas/alternate_payment_types.json
tap_toast/schemas/break_types.json
tap_toast/schemas/cash_drawers.json
tap_toast/schemas/cash_management_deposits.json
tap_toast/schemas/cash_management_entries.json
tap_toast/schemas/dining_options.json
tap_toast/schemas/discounts.json
tap_toast/schemas/employees.json
tap_toast/schemas/menu_groups.json
tap_toast/schemas/menu_items.json
tap_toast/schemas/menu_option_groups.json
tap_toast/schemas/menus.json
tap_toast/schemas/no_sale_reasons.json
tap_toast/schemas/orders.json
tap_toast/schemas/payments.json
tap_toast/schemas/payout_reasons.json
tap_toast/schemas/pre_modifier_groups.json
tap_toast/schemas/pre_modifiers.json
tap_toast/schemas/premodifier_groups.json
tap_toast/schemas/premodifiers.json
tap_toast/schemas/price_groups.json
tap_toast/schemas/printers.json
tap_toast/schemas/restaurant_services.json
tap_toast/schemas/restaurants.json
tap_toast/schemas/revenue_centers.json
tap_toast/schemas/sales_categories.json
tap_toast/schemas/service_areas.json
tap_toast/schemas/tables.json
tap_toast/schemas/tax_rates.json
tap_toast/schemas/tip_withholding.json
tap_toast/schemas/void_reasons.json