Metadata-Version: 1.1
Name: tap-toast
Version: 0.0.2
Summary: Singer.io tap for extracting data from the Toast API
Home-page: https://andyjiang.com
Author: @lambtron
Author-email: UNKNOWN
License: UNKNOWN
Platform: UNKNOWN
Classifier: Programming Language :: Python :: 3 :: Only
